hisense2mqtt/__init__.py
hisense2mqtt/__main__.py
hisense2mqtt/bridge.py
hisense2mqtt/config.py
hisense2mqtt/discovery.py
hisense_tv/__init__.py
hisense_tv/async_client.py
hisense_tv/cli.py
hisense_tv/client.py
hisense_tv/credentials.py
hisense_tv/discovery.py
hisense_tv/keys.py
hisense_tv/protocol.py
hisense_tv/topics.py
hisense_tv/wol.py
hisense_tv/config/__init__.py
hisense_tv/config/constants.py
hisense_tv/config/loader.py
hisense_tv/config/schema.py
hisense_tv/config/storage.py
myhisense_tv-1.6.0.dist-info/licenses/LICENSE
tests/__init__.py
tests/conftest.py
tests/test_config_flow.py
tests/test_coordinator.py
tests/test_diagnostics.py
tests/test_init.py
tests/test_media_player.py
tests/test_repairs.py
myhisense_tv-1.6.0.dist-info/METADATA
myhisense_tv-1.6.0.dist-info/WHEEL
myhisense_tv-1.6.0.dist-info/entry_points.txt
myhisense_tv-1.6.0.dist-info/top_level.txt
myhisense_tv-1.6.0.dist-info/RECORD
