Metadata-Version: 2.4
Name: myhisense-tv
Version: 1.6.0
Summary: Control Hisense/Vidaa Smart TVs via MQTT
Home-page: https://github.com/warrenrees/myhisense-tv
Author: Warren Rees
Author-email: 
Project-URL: Bug Tracker, https://github.com/warrenrees/myhisense-tv/issues
Project-URL: Documentation, https://github.com/warrenrees/myhisense-tv#readme
Project-URL: Source Code, https://github.com/warrenrees/myhisense-tv
Project-URL: Changelog, https://github.com/warrenrees/myhisense-tv/blob/main/CHANGELOG.md
Keywords: hisense myhisense vidaa tv mqtt smart-tv home-automation
Classifier: Development Status :: 4 - Beta
Classifier: Intended Audience :: Developers
Classifier: Intended Audience :: End Users/Desktop
Classifier: License :: OSI Approved :: MIT License
Classifier: Operating System :: OS Independent
Classifier: Programming Language :: Python :: 3
Classifier: Programming Language :: Python :: 3.8
Classifier: Programming Language :: Python :: 3.9
Classifier: Programming Language :: Python :: 3.10
Classifier: Programming Language :: Python :: 3.11
Classifier: Programming Language :: Python :: 3.12
Classifier: Topic :: Home Automation
Classifier: Topic :: Software Development :: Libraries :: Python Modules
Requires-Python: >=3.8
License-File: LICENSE
Requires-Dist: paho-mqtt>=1.6.0
Requires-Dist: pyyaml>=6.0
Dynamic: author
Dynamic: classifier
Dynamic: description
Dynamic: description-content-type
Dynamic: home-page
Dynamic: keywords
Dynamic: license-file
Dynamic: project-url
Dynamic: requires-dist
Dynamic: requires-python
Dynamic: summary
